[
  {
    "HasOnlineStore": true,
    "Type": "Shop",
    "SquareMeters": 0,
    "ID": "81f5ba10-5308-44a9-b696-e7bc4f2d35f5",
    "Address": {
      "Street": "Street name",
      "ZipCode": "Zip code",
      "City": "City",
      "Country": 164
    },
    "LegalForm": {
      "FormType": 0
    },
    "LinkedBuyer": {
      "Budget": 300000,
      "HasLoanApproval": true,
      "Type": "Buyer",
      "ID": "8469CB4A-0FEB-417B-9337-23994AF7EEDF",
      "Name": "John Doe",
      "Address": {
        "Street": "123 Maple Street",
        "ZipCode": "12345",
        "City": "Springfield",
        "Country": 163
      }
    },
    "LinkedSeller": {
      "AskingPrice": 350000,
      "Type": "Seller",
      "ID": "25E23DA1-9CF9-4D43-A82C-5E55F1904AA0",
      "Name": "Jane Smith",
      "Address": {
        "Street": "456 Oak Avenue",
        "ZipCode": "54321",
        "City": "Shelbyville",
        "Country": 163
      }
    },
    "ImagePath": "C:\\Users\\ludwi\\OneDrive\\Skrivbord\\testImage.png"
  },
  {
    "NumberOfClassrooms": 0,
    "Type": "School",
    "ParkingSpaces": 0,
    "ID": "80b144da-92b0-43fe-968b-47f258752eb7",
    "Address": {
      "Street": "Street name",
      "ZipCode": "Zip code",
      "City": "City",
      "Country": 164
    },
    "LegalForm": {
      "FormType": 0
    },
    "LinkedBuyer": {
      "Budget": 300000,
      "HasLoanApproval": true,
      "Type": "Buyer",
      "ID": "8469CB4A-0FEB-417B-9337-23994AF7EEDF",
      "Name": "John Doe",
      "Address": {
        "Street": "123 Maple Street",
        "ZipCode": "12345",
        "City": "Springfield",
        "Country": 163
      }
    },
    "LinkedSeller": {
      "AskingPrice": 350000,
      "Type": "Seller",
      "ID": "25E23DA1-9CF9-4D43-A82C-5E55F1904AA0",
      "Name": "Jane Smith",
      "Address": {
        "Street": "456 Oak Avenue",
        "ZipCode": "54321",
        "City": "Shelbyville",
        "Country": 163
      }
    },
    "ImagePath": "C:\\Users\\ludwi\\OneDrive\\Skrivbord\\testImage.png"
  },
  {
    "FloorLevel": 0,
    "Type": "Apartment",
    "NumberOfRooms": 0,
    "ID": "54174fae-79a8-454d-abf7-d302a9124da1",
    "Address": {
      "Street": "Street name",
      "ZipCode": "Zip code",
      "City": "City",
      "Country": 164
    },
    "LegalForm": {
      "FormType": 0
    },
    "LinkedBuyer": {
      "Budget": 300000,
      "HasLoanApproval": true,
      "Type": "Buyer",
      "ID": "8469CB4A-0FEB-417B-9337-23994AF7EEDF",
      "Name": "John Doe",
      "Address": {
        "Street": "123 Maple Street",
        "ZipCode": "12345",
        "City": "Springfield",
        "Country": 163
      }
    },
    "LinkedSeller": {
      "AskingPrice": 350000,
      "Type": "Seller",
      "ID": "25E23DA1-9CF9-4D43-A82C-5E55F1904AA0",
      "Name": "Jane Smith",
      "Address": {
        "Street": "456 Oak Avenue",
        "ZipCode": "54321",
        "City": "Shelbyville",
        "Country": 163
      }
    },
    "ImagePath": "C:\\Users\\ludwi\\OneDrive\\Skrivbord\\testImage.png"
  }
]